{
  "$schema": "https://static.modelcontextprotocol.io/schemas/2025-12-11/server.schema.json",
  "name": "io.github.tarunlnmiit/inbox-to-action",
  "description": "Agentic Gmail triage: classify, summarize, extract tasks, draft replies. Never sends.",
  "version": "0.2.5",
  "repository": {
    "url": "https://github.com/tarunlnmiit/inbox-to-action",
    "source": "github"
  },
  "packages": [
    {
      "registryType": "pypi",
      "identifier": "inbox-to-action",
      "version": "0.2.5",
      "transport": {
        "type": "stdio"
      },
      "runtimeHint": "python",
      "packageArguments": [
        { "type": "positional", "value": "mcp" }
      ]
    }
  ]
}
